markupfield_helpers/__init__.py
markupfield_helpers/admin.py
markupfield_helpers/apps.py
markupfield_helpers/helpers.py
markupfield_helpers/models.py
markupfield_helpers/tests.py
markupfield_helpers/views.py
markupfield_helpers/static/markupfield_helpers/css/syntax-highlighting.css
django_markupfield_helpers-0.1.1.dist-info/LICENSE
django_markupfield_helpers-0.1.1.dist-info/METADATA
django_markupfield_helpers-0.1.1.dist-info/WHEEL
django_markupfield_helpers-0.1.1.dist-info/top_level.txt
django_markupfield_helpers-0.1.1.dist-info/RECORD
