Metadata-Version: 2.1
Name: django-markupfield-helpers
Version: 0.1.1
Summary: A set of Django helpers that make it easier to get up and running quickly with django-markupfield
Home-page: https://github.com/mfcovington/django-markupfield-helpers
Author: Michael F. Covington
Author-email: mfcovington@gmail.com
License: BSD License
Keywords: markup markdown
Platform: UNKNOWN
Classifier: Development Status :: 3 - Alpha
Classifier: Environment :: Web Environment
Classifier: Framework :: Django
Classifier: Framework :: Django :: 1.11
Classifier: Framework :: Django :: 2.0
Classifier: Framework :: Django :: 2.1
Classifier: Intended Audience :: Science/Research
Classifier: License :: OSI Approved :: BSD License
Classifier: Operating System :: OS Independent
Classifier: Programming Language :: Python
Classifier: Programming Language :: Python :: 3
Classifier: Programming Language :: Python :: 3.2
Classifier: Programming Language :: Python :: 3.3
Classifier: Programming Language :: Python :: 3.4
Classifier: Programming Language :: Python :: 3.5
Classifier: Programming Language :: Python :: 3.6
Classifier: Programming Language :: Python :: 3.7
Classifier: Programming Language :: Python :: 3 :: Only
Classifier: Topic :: Documentation
Classifier: Topic :: Internet :: WWW/HTTP
Classifier: Topic :: Internet :: WWW/HTTP :: Dynamic Content
Requires-Dist: Django (>=1.11)
Requires-Dist: django-markupfield (>=1.3.5)
Requires-Dist: docutils (>=0.12)
Requires-Dist: markdown2 (>=2.3.0)
Requires-Dist: Pygments (>=2.0.2)
